ORForise/Aggregate_Compare.py
ORForise/Annotation_Compare.py
ORForise/Comparator.py
ORForise/GFF_Adder.py
ORForise/GFF_Intersector.py
ORForise/StORForise.py
ORForise/__init__.py
ORForise/utils.py
ORForise/ORForise_Analysis/__init__.py
ORForise/ORForise_Analysis/cds_checker.py
ORForise/ORForise_Analysis/gene_Lenghts.py
ORForise/ORForise_Analysis/genome_Metrics.py
ORForise/ORForise_Analysis/hypothetical_gene_predictions.py
ORForise/ORForise_Analysis/missed_Gene_Metrics.py
ORForise/ORForise_Analysis/parital_Match_Analysis.py
ORForise/ORForise_Analysis/result_File_Analysis.py
ORForise/ORForise_Analysis/start_Codon_Substitution.py
ORForise/Tools/__init__.py
ORForise/Tools/Augustus/Augustus.py
ORForise/Tools/Augustus/__init__.py
ORForise/Tools/Balrog/Balrog.py
ORForise/Tools/Balrog/__init__.py
ORForise/Tools/EasyGene/EasyGene.py
ORForise/Tools/EasyGene/__init__.py
ORForise/Tools/FGENESB/FGENESB.py
ORForise/Tools/FGENESB/__init__.py
ORForise/Tools/FragGeneScan/FragGeneScan.py
ORForise/Tools/FragGeneScan/__init__.py
ORForise/Tools/GFF/GFF.py
ORForise/Tools/GFF/__init__.py
ORForise/Tools/GLIMMER_3/GLIMMER_3.py
ORForise/Tools/GLIMMER_3/__init__.py
ORForise/Tools/GeneMark/GeneMark.py
ORForise/Tools/GeneMark/__init__.py
ORForise/Tools/GeneMark_HA/GeneMark_HA.py
ORForise/Tools/GeneMark_HA/__init__.py
ORForise/Tools/GeneMark_HMM/GeneMark_HMM.py
ORForise/Tools/GeneMark_HMM/__init__.py
ORForise/Tools/GeneMark_S/GeneMark_S.py
ORForise/Tools/GeneMark_S/__init__.py
ORForise/Tools/GeneMark_S_2/GeneMark_S_2.py
ORForise/Tools/GeneMark_S_2/__init__.py
ORForise/Tools/MetaGene/MetaGene.py
ORForise/Tools/MetaGene/__init__.py
ORForise/Tools/MetaGeneAnnotator/MetaGeneAnnotator.py
ORForise/Tools/MetaGeneAnnotator/__init__.py
ORForise/Tools/MetaGeneMark/MetaGeneMark.py
ORForise/Tools/MetaGeneMark/__init__.py
ORForise/Tools/Prodigal/Prodigal.py
ORForise/Tools/Prodigal/__init__.py
ORForise/Tools/Prokka/Prokka.py
ORForise/Tools/Prokka/__init__.py
ORForise/Tools/StORF_Reporter/StORF_Reporter.py
orforise-1.5.1.dist-info/licenses/LICENSE
orforise-1.5.1.dist-info/METADATA
orforise-1.5.1.dist-info/WHEEL
orforise-1.5.1.dist-info/entry_points.txt
orforise-1.5.1.dist-info/top_level.txt
orforise-1.5.1.dist-info/RECORD
