Metadata-Version: 2.4
Name: ORForise
Version: 1.5.1
Summary: ORForise - Platform for analysing and comparing Prokaryote CoDing Sequence (CDS) Gene Predictions.
Home-page: https://github.com/NickJD/ORForise
Author: Nicholas Dimonaco
Author-email: nicholas@dimonaco.co.uk
Project-URL: Bug Tracker, https://github.com/NickJD/ORForise/issues
Classifier: Programming Language :: Python :: 3
Classifier: License :: OSI Approved :: GNU General Public License v3 (GPLv3)
Classifier: Operating System :: OS Independent
Requires-Python: >=3.6
License-File: LICENSE
Requires-Dist: numpy
Dynamic: license-file
